fastxtend/__init__.py
fastxtend/_modidx.py
fastxtend/basics.py
fastxtend/imports.py
fastxtend/losses.py
fastxtend/metrics.py
fastxtend/multiloss.py
fastxtend/patches.py
fastxtend/schedulers.py
fastxtend/test_utils.py
fastxtend/torch_core.py
fastxtend/transform.py
fastxtend/utils.py
fastxtend/audio/__init__.py
fastxtend/audio/all.py
fastxtend/audio/augment.py
fastxtend/audio/core.py
fastxtend/audio/data.py
fastxtend/audio/learner.py
fastxtend/audio/mixup.py
fastxtend/callback/__init__.py
fastxtend/callback/all.py
fastxtend/callback/amp.py
fastxtend/callback/channelslast.py
fastxtend/callback/compiler.py
fastxtend/callback/cutmixup.py
fastxtend/callback/ema.py
fastxtend/callback/gradaccum.py
fastxtend/callback/lr_finder.py
fastxtend/callback/profiler.py
fastxtend/callback/progresize.py
fastxtend/callback/simpleprofiler.py
fastxtend/callback/tracker.py
fastxtend/callback/utils.py
fastxtend/data/__init__.py
fastxtend/data/all.py
fastxtend/data/loader.py
fastxtend/data/transforms.py
fastxtend/ffcv/__init__.py
fastxtend/ffcv/all.py
fastxtend/ffcv/epoch_iterator.py
fastxtend/ffcv/fields.py
fastxtend/ffcv/fx.py
fastxtend/ffcv/inference.py
fastxtend/ffcv/loader.py
fastxtend/ffcv/operations.py
fastxtend/ffcv/transforms.py
fastxtend/ffcv/utils.py
fastxtend/ffcv/writer.py
fastxtend/optimizer/__init__.py
fastxtend/optimizer/adan.py
fastxtend/optimizer/all.py
fastxtend/optimizer/eightbit.py
fastxtend/optimizer/foreach.py
fastxtend/optimizer/fused.py
fastxtend/optimizer/lion.py
fastxtend/optimizer/sophia.py
fastxtend/optimizer/stableadam.py
fastxtend/optimizer/torchscript.py
fastxtend/text/__init__.py
fastxtend/text/all.py
fastxtend/text/huggingface.py
fastxtend/vision/__init__.py
fastxtend/vision/all.py
fastxtend/vision/data.py
fastxtend/vision/augment/__init__.py
fastxtend/vision/augment/all.py
fastxtend/vision/augment/batch.py
fastxtend/vision/augment/itemtensor.py
fastxtend/vision/models/__init__.py
fastxtend/vision/models/all.py
fastxtend/vision/models/attention_modules.py
fastxtend-0.1.7.dist-info/LICENSE
fastxtend-0.1.7.dist-info/METADATA
fastxtend-0.1.7.dist-info/WHEEL
fastxtend-0.1.7.dist-info/entry_points.txt
fastxtend-0.1.7.dist-info/top_level.txt
fastxtend-0.1.7.dist-info/RECORD
