Metadata-Version: 2.1
Name: fastxtend
Version: 0.1.7
Summary: Train fastai models faster (and other useful tools)
Home-page: https://github.com/warner-benjamin/fastxtend
Author: Benjamin Warner
Author-email: me@benjaminwarner.dev
License: MIT License
Project-URL: Documentation, https://fastxtend.benjaminwarner.dev/
Keywords: fastai pytorch deep-learning
Classifier: Development Status :: 4 - Beta
Classifier: Intended Audience :: Developers
Classifier: Natural Language :: English
Classifier: Programming Language :: Python :: 3.8
Classifier: Programming Language :: Python :: 3.9
Classifier: Programming Language :: Python :: 3.10
Classifier: Programming Language :: Python :: 3.11
Classifier: License :: OSI Approved :: MIT License
Requires-Python: >=3.8
License-File: LICENSE
Requires-Dist: pandas >=2.0.3
Requires-Dist: fastcore >=1.5.27
Requires-Dist: fastai >=2.7.9
Requires-Dist: torch >=1.13.1
Provides-Extra: all
Requires-Dist: timm >=0.9.5 ; extra == 'all'
Requires-Dist: kornia >=0.7.0 ; extra == 'all'
Requires-Dist: ffcv >=1.0.2 ; extra == 'all'
Requires-Dist: librosa >=0.10.1 ; extra == 'all'
Requires-Dist: torchaudio >=2.0.1 ; extra == 'all'
Requires-Dist: primePy >=1.3 ; extra == 'all'
Requires-Dist: colorednoise >=2.0 ; extra == 'all'
Requires-Dist: soundfile >=0.10.3 ; extra == 'all'
Requires-Dist: matplotlib <3.8 ; extra == 'all'
Requires-Dist: transformers >=4.32.0 ; extra == 'all'
Requires-Dist: datasets >=2.14.3 ; extra == 'all'
Requires-Dist: wandb >=0.15.10 ; extra == 'all'
Requires-Dist: rich >=13.6.0 ; extra == 'all'
Requires-Dist: typer >=0.9.0 ; extra == 'all'
Requires-Dist: bitsandbytes >=0.41.0 ; extra == 'all'
Provides-Extra: audio
Requires-Dist: librosa >=0.10.1 ; extra == 'audio'
Requires-Dist: torchaudio >=2.0.1 ; extra == 'audio'
Requires-Dist: primePy >=1.3 ; extra == 'audio'
Requires-Dist: colorednoise >=2.0 ; extra == 'audio'
Requires-Dist: soundfile >=0.10.3 ; extra == 'audio'
Requires-Dist: matplotlib <3.8 ; extra == 'audio'
Provides-Extra: dev
Requires-Dist: timm >=0.9.5 ; extra == 'dev'
Requires-Dist: kornia >=0.7.0 ; extra == 'dev'
Requires-Dist: ffcv >=1.0.2 ; extra == 'dev'
Requires-Dist: librosa >=0.10.1 ; extra == 'dev'
Requires-Dist: torchaudio >=2.0.1 ; extra == 'dev'
Requires-Dist: primePy >=1.3 ; extra == 'dev'
Requires-Dist: colorednoise >=2.0 ; extra == 'dev'
Requires-Dist: soundfile >=0.10.3 ; extra == 'dev'
Requires-Dist: matplotlib <3.8 ; extra == 'dev'
Requires-Dist: transformers >=4.32.0 ; extra == 'dev'
Requires-Dist: datasets >=2.14.3 ; extra == 'dev'
Requires-Dist: wandb >=0.15.10 ; extra == 'dev'
Requires-Dist: rich >=13.6.0 ; extra == 'dev'
Requires-Dist: typer >=0.9.0 ; extra == 'dev'
Requires-Dist: bitsandbytes >=0.41.0 ; extra == 'dev'
Requires-Dist: nbdev >=2.3.12 ; extra == 'dev'
Provides-Extra: ffcv
Requires-Dist: timm >=0.9.5 ; extra == 'ffcv'
Requires-Dist: kornia >=0.7.0 ; extra == 'ffcv'
Requires-Dist: ffcv >=1.0.2 ; extra == 'ffcv'
Provides-Extra: text
Requires-Dist: transformers >=4.32.0 ; extra == 'text'
Requires-Dist: datasets >=2.14.3 ; extra == 'text'
Provides-Extra: vision
Requires-Dist: timm >=0.9.5 ; extra == 'vision'
Requires-Dist: kornia >=0.7.0 ; extra == 'vision'
